pytabify/__init__.py
pytabify/core/__init__.py
pytabify/core/datatable.py
pytabify/core/dt_field.py
pytabify/core/dt_header.py
pytabify/core/dt_row.py
pytabify/core/dt_schema.py
pytabify/creator.py
pytabify/io/file_formats.py
pytabify/io/interfaces/__init__.py
pytabify/io/interfaces/read.py
pytabify/io/interfaces/save.py
pytabify/io/strategies/__init__.py
pytabify/io/strategies/reading.py
pytabify/io/strategies/saving.py
pytabify/saver.py
pytabify/utils/__init__.py
pytabify/utils/errors.py
pytabify/utils/observer.py
pytabify/utils/validation.py
pytabify-1.0.1.dist-info/LICENSE
pytabify-1.0.1.dist-info/METADATA
pytabify-1.0.1.dist-info/WHEEL
pytabify-1.0.1.dist-info/RECORD
