Metadata-Version: 2.3
Name: pytabify
Version: 1.0.1
Summary: pytabify es una librería de propósito general para la manipulación, transformación y análisis de datos tabulares obtenidos a través de diversos formatos de archivo (CSV, JSON, Excel, etc.). Ofrece una API intuitiva y flexible que permite crear, validar y persistir estructuras de datos (DataTables), facilitando su integración en proyectos de automatización de pruebas, scripts y aplicaciones de análisis de datos.
License: MIT License
Author: Angel Gerardo Molina Valdez
Author-email: angelgerardomolinavaldez@gmail.com
Requires-Python: >=3.9
Classifier: License :: Other/Proprietary License
Classifier: Programming Language :: Python :: 3
Classifier: Programming Language :: Python :: 3.9
Classifier: Programming Language :: Python :: 3.10
Classifier: Programming Language :: Python :: 3.11
Classifier: Programming Language :: Python :: 3.12
Classifier: Programming Language :: Python :: 3.13
Requires-Dist: jsonschema (>=4.23.0,<5.0.0)
Requires-Dist: openpyxl (>=3.1.5,<4.0.0)
Project-URL: Repository, https://github.com/angel-valdezzz/pytabify
